{
    "package": {
        "elements": {
            "chunks": [
                {
                    "name": "head",
                    "category": "o_global"
                },{
                    "name": "header",
                    "category": "o_global"
                },{
                    "name": "script",
                    "category": "o_global"
                },{
                    "name": "footer",
                    "category": "o_global"
                }
            ],

            "categories": [
                {
                    "name": "o_global",
                    "parent": "03-organisms"
                }
            ]
        }
    }
}